<annotation verified="no">
  <folder>JPEGImages</folder>
  <filename>&#23736;&#24120;&#27877;</filename>
  <path>D:\project\keras-yolo3-master\VOCdevkit\VOC2007\JPEGImages\&#23736;&#24120;&#27877;.jpg</path>
  <source>
    <database>Unknown</database>
  </source>
  <size>
    <width>280</width>
    <height>85</height>
    <depth>3</depth>
  </size>
  <segmented>0</segmented>
  <object>
    <name>chinese</name>
    <pose>Unspecified</pose>
    <truncated>0</truncated>
    <difficult>0</difficult>
    <bndbox>
      <xmin>11</xmin>
      <ymin>8</ymin>
      <xmax>45</xmax>
      <ymax>39</ymax>
    </bndbox>
  </object>
  <object>
    <name>chinese</name>
    <pose>Unspecified</pose>
    <truncated>0</truncated>
    <difficult>0</difficult>
    <bndbox>
      <xmin>13</xmin>
      <ymin>48</ymin>
      <xmax>49</xmax>
      <ymax>71</ymax>
    </bndbox>
  </object>
  <object>
    <name>chinese</name>
    <pose>Unspecified</pose>
    <truncated>0</truncated>
    <difficult>0</difficult>
    <bndbox>
      <xmin>49</xmin>
      <ymin>10</ymin>
      <xmax>81</xmax>
      <ymax>37</ymax>
    </bndbox>
  </object>
  <object>
    <name>chinese</name>
    <pose>Unspecified</pose>
    <truncated>0</truncated>
    <difficult>0</difficult>
    <bndbox>
      <xmin>93</xmin>
      <ymin>35</ymin>
      <xmax>126</xmax>
      <ymax>67</ymax>
    </bndbox>
  </object>
  <object>
    <name>chinese</name>
    <pose>Unspecified</pose>
    <truncated>0</truncated>
    <difficult>0</difficult>
    <bndbox>
      <xmin>167</xmin>
      <ymin>64</ymin>
      <xmax>203</xmax>
      <ymax>83</ymax>
    </bndbox>
  </object>
  <object>
    <name>chinese</name>
    <pose>Unspecified</pose>
    <truncated>0</truncated>
    <difficult>0</difficult>
    <bndbox>
      <xmin>212</xmin>
      <ymin>30</ymin>
      <xmax>248</xmax>
      <ymax>58</ymax>
    </bndbox>
  </object>
</annotation>
